pytv/Converter.py
pytv/ModuleLoader.py
pytv/__init__.py
pytv/utils.py
verithon-2.2.dist-info/LICENSE
verithon-2.2.dist-info/METADATA
verithon-2.2.dist-info/WHEEL
verithon-2.2.dist-info/top_level.txt
verithon-2.2.dist-info/RECORD
