Metadata-Version: 2.1
Name: verithon
Version: 2.2
Summary: RTL Auto-generation with Verilog Embedded in Python
Home-page: https://github.com/autohdw/Voldelog.git
Author: JiaYanXu
Author-email: jiayanxu@seu.edu.cn
License: MIT
Requires-Python: >=3.6
License-File: LICENSE
